finceptapi/__init__.py
finceptapi/api.py
finceptapi-0.1.2.dist-info/LICENSE
finceptapi-0.1.2.dist-info/METADATA
finceptapi-0.1.2.dist-info/WHEEL
finceptapi-0.1.2.dist-info/top_level.txt
finceptapi-0.1.2.dist-info/RECORD
