Metadata-Version: 2.1
Name: finceptapi
Version: 0.1.2
Summary: A Python client library for Fincept API
Home-page: https://github.com/Fincept-Corporation/finceptapi
Author: Fincept Corporation
Author-email: support@fihcept.in
Classifier: Programming Language :: Python :: 3
Classifier: License :: OSI Approved :: MIT License
Classifier: Operating System :: OS Independent
Requires-Python: >=3.6
License-File: LICENSE
Requires-Dist: requests
Requires-Dist: python-dotenv
